kgrok/__init__.py
kgrok/local.py
kgrok/messages.py
kgrok/remote.py
kgrok-0.1.5.data/data/share/man/man1/kgrok.1
kgrok-0.1.5.dist-info/licenses/LICENSE.txt
kgrok-0.1.5.dist-info/METADATA
kgrok-0.1.5.dist-info/WHEEL
kgrok-0.1.5.dist-info/entry_points.txt
kgrok-0.1.5.dist-info/top_level.txt
kgrok-0.1.5.dist-info/RECORD
