Metadata-Version: 2.4
Name: kgrok
Version: 0.1.5
Summary: forward local processes into k8s cluster
Author: Daniel Golding
License-Expression: MIT
Project-URL: Homepage, https://github.com/cakemanny/kgrok
Project-URL: Repository, https://github.com/cakemanny/kgrok.git
Keywords: kubernetes,proxy
Classifier: Development Status :: 3 - Alpha
Classifier: Environment :: Console
Classifier: Intended Audience :: Developers
Classifier: Topic :: Internet :: Proxy Servers
Classifier: Programming Language :: Python :: 3
Classifier: Programming Language :: Python :: 3 :: Only
Classifier: Programming Language :: Python :: 3.12
Requires-Python: >=3.12
License-File: LICENSE.txt
Requires-Dist: click
Requires-Dist: lightkube
Requires-Dist: trio
Dynamic: license-file
Dynamic: requires-dist
